pyMAWP/__init__.py
pyMAWP/pyMAWP.py
pyMAWP-0.1.dist-info/LICENSE
pyMAWP-0.1.dist-info/METADATA
pyMAWP-0.1.dist-info/WHEEL
pyMAWP-0.1.dist-info/top_level.txt
pyMAWP-0.1.dist-info/RECORD
