Metadata-Version: 2.1
Name: pyMAWP
Version: 0.1
Summary: Vessel MAWP calculations
Home-page: https://github.com/kevindorma/pyMAWP
Author: Kevin Dorma
Author-email: kevin@kevindorma.ca
License: MIT
Download-URL: https://github.com/kevindorma/pyMAWP/archive/v0.1.tar.gz
Keywords: vessel,engineering,MAWP
Platform: UNKNOWN
Requires-Dist: pandas
Requires-Dist: scipy
